mdpaper/__init__.py
mdpaper/filters.py
mdpaper/main.py
mdpaper/settings.py
mdpaper-0.0.5.dist-info/entry_points.txt
mdpaper-0.0.5.dist-info/WHEEL
mdpaper-0.0.5.dist-info/METADATA
mdpaper-0.0.5.dist-info/RECORD
